autoscreenshot/__init__.py
autoscreenshot/__main__.py
autoscreenshot-0.1.2.dist-info/WHEEL
autoscreenshot-0.1.2.dist-info/METADATA
autoscreenshot-0.1.2.dist-info/RECORD
